sbl_optimizer/__init__.py
sbl_optimizer/config.py
sbl_optimizer/heat_solver.py
sbl_optimizer/io.py
sbl_optimizer/main.py
sbl_optimizer/utils.py
sbl_optimizer/assets/config.json
sbl_optimizer/assets/config.md
sbl_optimizer/assets/sample.jpg
sbl_optimizer-0.2.2.dist-info/licenses/LICENSE
sbl_optimizer-0.2.2.dist-info/METADATA
sbl_optimizer-0.2.2.dist-info/WHEEL
sbl_optimizer-0.2.2.dist-info/entry_points.txt
sbl_optimizer-0.2.2.dist-info/top_level.txt
sbl_optimizer-0.2.2.dist-info/RECORD
