Metadata-Version: 2.4
Name: sbl-optimizer
Version: 0.2.2
Summary: Pattern optimizer based on thermal simulations for Swell by Light
Author-email: Sosuke Ichihashi <pengu1n.i843@gmail.com>
Maintainer-email: Sosuke Ichihashi <pengu1n.i843@gmail.com>
License-Expression: MIT
Project-URL: HomePage, https://sites.gatech.edu/futurefeelings/2025/03/07/swell-by-light-tei-25/
Project-URL: Paper, https://dl.acm.org/doi/10.1145/3689050.3704420
Project-URL: Repository, https://github.com/sosucat/sbl-optimizer
Project-URL: Author, https://sosuke-ichihashi.com/
Keywords: hci,fabrication,diy,swell by light,heat transfer
Classifier: Development Status :: 4 - Beta
Classifier: Programming Language :: Python
Requires-Python: <3.12,>=3.9
License-File: LICENSE
Requires-Dist: numpy<2.3,>=1.24
Requires-Dist: pillow<12.0,>=9.5
Requires-Dist: matplotlib<3.11,>=3.7
Dynamic: license-file
